pontus/__init__.py
pontus/_compat.py
pontus/amazon_s3_file_validator.py
pontus/amazon_s3_signed_request.py
pontus/exceptions.py
pontus/validators.py
Pontus-4.1.0.dist-info/LICENSE
Pontus-4.1.0.dist-info/METADATA
Pontus-4.1.0.dist-info/WHEEL
Pontus-4.1.0.dist-info/top_level.txt
Pontus-4.1.0.dist-info/RECORD
