Metadata-Version: 2.1
Name: Pontus
Version: 4.1.0
Summary: Flask utility for Amazon S3.
Home-page: https://github.com/fastmonkeys/pontus
Author: Vesa Uimonen
Author-email: vesa@fastmonkeys.com
License: MIT
Platform: any
Classifier: Environment :: Web Environment
Classifier: Intended Audience :: Developers
Classifier: License :: OSI Approved :: MIT License
Classifier: Operating System :: OS Independent
Classifier: Programming Language :: Python
Classifier: Topic :: Internet :: WWW/HTTP :: Dynamic Content
Classifier: Topic :: Software Development :: Libraries :: Python Modules
License-File: LICENSE
Requires-Dist: Flask >=0.10.1
Requires-Dist: python-magic >=0.4.6
Requires-Dist: boto3 >=1.4.7
Provides-Extra: test
Requires-Dist: flexmock >=0.9.7 ; extra == 'test'
Requires-Dist: freezegun >=0.1.18 ; extra == 'test'
Requires-Dist: py >=1.4.20 ; extra == 'test'
Requires-Dist: pytest >=2.5.2 ; extra == 'test'
Requires-Dist: moto[s3] <5,>=4 ; extra == 'test'
